discord_voicebot/__init__.py
discord_voicebot/__main__.py
discord_voicebot/bot.py
discord_voicebot/util.py
discord_voicebot-0.3.0.dist-info/METADATA
discord_voicebot-0.3.0.dist-info/WHEEL
discord_voicebot-0.3.0.dist-info/entry_points.txt
discord_voicebot-0.3.0.dist-info/licenses/LICENSE
discord_voicebot-0.3.0.dist-info/RECORD
