Metadata-Version: 2.4
Name: discord-voicebot
Version: 0.3.0
Summary: Discord bot that sends notifications whenever a user enters a voice channel
Project-URL: Homepage, https://github.com/IAmTheMitchell/voicebot
Project-URL: Bug Tracker, https://github.com/IAmTheMitchell/voicebot/issues
Project-URL: Changelog, https://github.com/IAmTheMitchell/voicebot/blob/main/CHANGELOG.md
Author: Dan Petrolito
Author-email: Mitchell Carlson <mitchell.carlson.pro@gmail.com>
License-Expression: MIT
License-File: LICENSE
Classifier: Operating System :: OS Independent
Classifier: Programming Language :: Python :: 3
Requires-Python: >=3.11
Requires-Dist: discord-py[voice]>=2.5.2
Requires-Dist: httpx>=0.28.1
Requires-Dist: python-dotenv>=1.1.1
